{
  "publicPath": "/",
  "all": [
    "js/vendor.892b70d6.js",
    "css/vendor.8d2b1356.css",
    "fonts/materialdesignicons-webfont.d8e8e0f7.woff",
    "fonts/materialdesignicons-webfont.e9db4005.woff2",
    "fonts/flUhRq6tzZclQEJ-Vdg-IuiaDsNa.81048c6d.woff",
    "fonts/la-solid-900.89363487.woff",
    "fonts/flUhRq6tzZclQEJ-Vdg-IuiaDsNcIhQ8tQ.12730e02.woff2",
    "fonts/la-brands-400.925b340f.woff",
    "fonts/la-solid-900.3efd5ba1.woff2",
    "fonts/la-brands-400.3a8109c4.woff2",
    "fonts/themify.29b39089.woff",
    "js/app.766d2eb0.js",
    "js/71.90c5e4ff.js",
    "js/678.54fbb84a.js",
    "icons/apple-launch-1620x2160.png",
    "js/374.2c360e5a.js",
    "js/745.2730c013.js",
    "js/573.5e0891fb.js",
    "fonts/KFOlCnqEu92Fr1MmEU9fBBc-.ddd11dab.woff",
    "fonts/KFOkCnqEu92Fr1MmgVxIIzQ.9391e6e2.woff",
    "fonts/KFOlCnqEu92Fr1MmYUtfBBc-.b555d228.woff",
    "fonts/KFOlCnqEu92Fr1MmSU5fBBc-.877b9231.woff",
    "fonts/KFOlCnqEu92Fr1MmWUlfBBc-.0344cc3c.woff",
    "fonts/KFOmCnqEu92Fr1Mu4mxM.9b78ea3b.woff",
    "js/969.1bc15ffb.js",
    "favicon.ico",
    "fonts/la-regular-400.aa859c0d.woff",
    "js/9.f29d0d90.js",
    "js/703.40489853.js",
    "icons/apple-launch-2048x2732.png",
    "icons/safari-pinned-tab.svg",
    "fonts/la-regular-400.8dc1cedf.woff2",
    "js/687.34867be0.js",
    "js/780.092080b3.js",
    "js/31.570d9e0a.js",
    "js/853.70a71934.js",
    "icons/apple-launch-1668x2388.png",
    "icons/apple-launch-1668x2224.png",
    "icons/apple-launch-1536x2048.png",
    "icons/icon-512x512.png",
    "icons/apple-launch-1170x2532.png",
    "js/597.66cd945b.js",
    "js/967.5ead2cfa.js",
    "js/719.ba87630b.js",
    "icons/apple-launch-1284x2778.png",
    "icons/apple-launch-1242x2688.png",
    "icons/apple-launch-1242x2208.png",
    "icons/icon-384x384.png",
    "icons/apple-launch-1125x2436.png",
    "js/984.d363d4fc.js",
    "icons/apple-launch-828x1792.png",
    "icons/apple-launch-750x1334.png",
    "icons/icon-256x256.png",
    "icons/icon-192x192.png",
    "icons/apple-icon-180x180.png",
    "icons/ms-icon-144x144.png",
    "icons/apple-icon-167x167.png",
    "icons/favicon-128x128.png",
    "icons/icon-128x128.png",
    "icons/apple-icon-152x152.png",
    "icons/apple-icon-120x120.png",
    "icons/favicon-96x96.png",
    "manifest.json",
    "icons/favicon-32x32.png",
    "icons/favicon-16x16.png",
    "css/app.31d6cfe0.css"
  ],
  "initial": [
    "css/vendor.8d2b1356.css",
    "js/vendor.892b70d6.js",
    "css/app.31d6cfe0.css",
    "js/app.766d2eb0.js"
  ],
  "async": [
    "js/71.90c5e4ff.js",
    "js/678.54fbb84a.js",
    "js/374.2c360e5a.js",
    "js/745.2730c013.js",
    "js/573.5e0891fb.js",
    "js/969.1bc15ffb.js",
    "js/9.f29d0d90.js",
    "js/703.40489853.js",
    "js/687.34867be0.js",
    "js/780.092080b3.js",
    "js/31.570d9e0a.js",
    "js/853.70a71934.js",
    "js/597.66cd945b.js",
    "js/967.5ead2cfa.js",
    "js/719.ba87630b.js",
    "js/984.d363d4fc.js"
  ],
  "modules": {
    "15102255": [
      1,
      0,
      3,
      2,
      10,
      9,
      7,
      31,
      26,
      8,
      5,
      19,
      21,
      23,
      18,
      22,
      20,
      6,
      4
    ],
    "16426742": [
      1,
      0,
      3,
      2,
      10,
      9,
      7,
      31,
      26,
      8,
      5,
      19,
      21,
      23,
      18,
      22,
      20,
      6,
      4
    ],
    "30176681": [
      1,
      0,
      3,
      2,
      10,
      9,
      7,
      31,
      26,
      8,
      5,
      19,
      21,
      23,
      18,
      22,
      20,
      6,
      4
    ],
    "30955262": [
      1,
      0,
      3,
      2,
      10,
      9,
      7,
      31,
      26,
      8,
      5,
      19,
      21,
      23,
      18,
      22,
      20,
      6,
      4
    ],
    "38399114": [
      1,
      0,
      3,
      2,
      10,
      9,
      7,
      31,
      26,
      8,
      5,
      19,
      21,
      23,
      18,
      22,
      20,
      6,
      4
    ],
    "39306791": [
      13
    ],
    "46389116": [
      1,
      0,
      3,
      2,
      10,
      9,
      7,
      31,
      26,
      8,
      5,
      19,
      21,
      23,
      18,
      22,
      20,
      6,
      4
    ],
    "52550801": [
      1,
      0,
      3,
      2,
      10,
      9,
      7,
      31,
      26,
      8,
      5,
      19,
      21,
      23,
      18,
      22,
      20,
      6,
      4
    ],
    "53860272": [
      1,
      0,
      3,
      2,
      10,
      9,
      7,
      31,
      26,
      8,
      5,
      19,
      21,
      23,
      18,
      22,
      20,
      6,
      4
    ],
    "68542209": [
      1,
      0,
      3,
      2,
      10,
      9,
      7,
      31,
      26,
      8,
      5,
      19,
      21,
      23,
      18,
      22,
      20,
      6,
      4
    ],
    "68701296": [
      65,
      11
    ],
    "44e4742c": [
      65,
      11
    ],
    "2a20f028": [
      1,
      0,
      3,
      2,
      10,
      9,
      7,
      31,
      26,
      8,
      5,
      19,
      21,
      23,
      18,
      22,
      20,
      6,
      4
    ],
    "bbc82f7a": [
      1,
      0,
      3,
      2,
      10,
      9,
      7,
      31,
      26,
      8,
      5,
      19,
      21,
      23,
      18,
      22,
      20,
      6,
      4
    ],
    "daf8ce56": [
      65,
      11
    ],
    "eb1eb21a": [
      65,
      11
    ],
    "58e29777": [
      1,
      0,
      3,
      2,
      10,
      9,
      7,
      31,
      26,
      8,
      5,
      19,
      21,
      23,
      18,
      22,
      20,
      6,
      4
    ],
    "6274403b": [
      65,
      11
    ],
    "4ac89350": [
      65,
      11
    ],
    "41ca4e5c": [
      65,
      11
    ],
    "44c90ad0": [
      65,
      11
    ],
    "181e18ac": [
      65,
      11
    ],
    "4fa83af9": [
      65,
      11
    ],
    "0a0525d0": [
      1,
      0,
      3,
      2,
      10,
      9,
      7,
      31,
      26,
      8,
      5,
      19,
      21,
      23,
      18,
      22,
      20,
      6,
      4
    ],
    "3e6de3e0": [
      65,
      11
    ],
    "f558ceb4": [
      1,
      0,
      3,
      2,
      10,
      9,
      7,
      31,
      26,
      8,
      5,
      19,
      21,
      23,
      18,
      22,
      20,
      6,
      4
    ],
    "137c29b9": [
      1,
      0,
      3,
      2,
      10,
      9,
      7,
      31,
      26,
      8,
      5,
      19,
      21,
      23,
      18,
      22,
      20,
      6,
      4
    ],
    "0c97b460": [
      1,
      0,
      3,
      2,
      10,
      9,
      7,
      31,
      26,
      8,
      5,
      19,
      21,
      23,
      18,
      22,
      20,
      6,
      4
    ],
    "2a821055": [
      1,
      0,
      3,
      2,
      10,
      9,
      7,
      31,
      26,
      8,
      5,
      19,
      21,
      23,
      18,
      22,
      20,
      6,
      4
    ],
    "a6010c1e": [
      1,
      0,
      3,
      2,
      10,
      9,
      7,
      31,
      26,
      8,
      5,
      19,
      21,
      23,
      18,
      22,
      20,
      6,
      4
    ],
    "1de1ccb0": [
      1,
      0,
      3,
      2,
      10,
      9,
      7,
      31,
      26,
      8,
      5,
      19,
      21,
      23,
      18,
      22,
      20,
      6,
      4
    ],
    "dd269b92": [
      1,
      0,
      3,
      2,
      10,
      9,
      7,
      31,
      26,
      8,
      5,
      19,
      21,
      23,
      18,
      22,
      20,
      6,
      4
    ],
    "176d0656": [
      1,
      0,
      3,
      2,
      10,
      9,
      7,
      31,
      26,
      8,
      5,
      19,
      21,
      23,
      18,
      22,
      20,
      6,
      4
    ],
    "99c6d5e6": [
      1,
      0,
      3,
      2,
      10,
      9,
      7,
      31,
      26,
      8,
      5,
      19,
      21,
      23,
      18,
      22,
      20,
      6,
      4
    ],
    "63851fea": [
      1,
      0,
      3,
      2,
      10,
      9,
      7,
      31,
      26,
      8,
      5,
      19,
      21,
      23,
      18,
      22,
      20,
      6,
      4
    ],
    "4dbf384c": [
      1,
      0,
      3,
      2,
      10,
      9,
      7,
      31,
      26,
      8,
      5,
      19,
      21,
      23,
      18,
      22,
      20,
      6,
      4
    ],
    "f44942aa": [
      1,
      0,
      3,
      2,
      10,
      9,
      7,
      31,
      26,
      8,
      5,
      19,
      21,
      23,
      18,
      22,
      20,
      6,
      4
    ],
    "2a1c9ed2": [
      1,
      0,
      3,
      2,
      10,
      9,
      7,
      31,
      26,
      8,
      5,
      19,
      21,
      23,
      18,
      22,
      20,
      6,
      4
    ],
    "70d3b7da": [
      1,
      0,
      3,
      2,
      10,
      9,
      7,
      31,
      26,
      8,
      5,
      19,
      21,
      23,
      18,
      22,
      20,
      6,
      4
    ],
    "44a08cda": [
      1,
      0,
      3,
      2,
      10,
      9,
      7,
      31,
      26,
      8,
      5,
      19,
      21,
      23,
      18,
      22,
      20,
      6,
      4
    ],
    "3bf4029d": [
      1,
      0,
      3,
      2,
      10,
      9,
      7,
      31,
      26,
      8,
      5,
      19,
      21,
      23,
      18,
      22,
      20,
      6,
      4
    ],
    "7b5729f0": [
      1,
      0,
      3,
      2,
      10,
      9,
      7,
      31,
      26,
      8,
      5,
      19,
      21,
      23,
      18,
      22,
      20,
      6,
      4
    ],
    "5f0ecac2": [
      1,
      0,
      3,
      2,
      10,
      9,
      7,
      31,
      26,
      8,
      5,
      19,
      21,
      23,
      18,
      22,
      20,
      6,
      4
    ],
    "8981a962": [
      1,
      0,
      3,
      2,
      10,
      9,
      7,
      31,
      26,
      8,
      5,
      19,
      21,
      23,
      18,
      22,
      20,
      6,
      4
    ],
    "b82320ee": [
      1,
      0,
      3,
      2,
      10,
      9,
      7,
      31,
      26,
      8,
      5,
      19,
      21,
      23,
      18,
      22,
      20,
      6,
      4
    ],
    "43b9b253": [
      1,
      0,
      3,
      2,
      10,
      9,
      7,
      31,
      26,
      8,
      5,
      19,
      21,
      23,
      18,
      22,
      20,
      6,
      4
    ],
    "42dbfe15": [
      1,
      0,
      3,
      2,
      10,
      9,
      7,
      31,
      26,
      8,
      5,
      19,
      21,
      23,
      18,
      22,
      20,
      6,
      4
    ],
    "1e8ddfda": [
      1,
      0,
      3,
      2,
      10,
      9,
      7,
      31,
      26,
      8,
      5,
      19,
      21,
      23,
      18,
      22,
      20,
      6,
      4
    ],
    "66e51283": [
      1,
      0,
      3,
      2,
      10,
      9,
      7,
      31,
      26,
      8,
      5,
      19,
      21,
      23,
      18,
      22,
      20,
      6,
      4
    ],
    "5c1ec413": [
      1,
      0,
      3,
      2,
      10,
      9,
      7,
      31,
      26,
      8,
      5,
      19,
      21,
      23,
      18,
      22,
      20,
      6,
      4
    ],
    "3871c08f": [
      1,
      0,
      3,
      2,
      10,
      9,
      7,
      31,
      26,
      8,
      5,
      19,
      21,
      23,
      18,
      22,
      20,
      6,
      4
    ],
    "6b5d452e": [
      65,
      11
    ],
    "2e16110c": [
      1,
      0,
      3,
      2,
      10,
      9,
      7,
      31,
      26,
      8,
      5,
      19,
      21,
      23,
      18,
      22,
      20,
      6,
      4
    ],
    "4294155f": [
      1,
      0,
      3,
      2,
      10,
      9,
      7,
      31,
      26,
      8,
      5,
      19,
      21,
      23,
      18,
      22,
      20,
      6,
      4
    ],
    "563d4cd9": [
      1,
      0,
      3,
      2,
      10,
      9,
      7,
      31,
      26,
      8,
      5,
      19,
      21,
      23,
      18,
      22,
      20,
      6,
      4
    ],
    "3313f20a": [
      1,
      0,
      3,
      2,
      10,
      9,
      7,
      31,
      26,
      8,
      5,
      19,
      21,
      23,
      18,
      22,
      20,
      6,
      4
    ],
    "cd3bddaa": [
      65,
      11
    ],
    "046456fe": [
      65,
      11
    ],
    "0b3aba6e": [
      1,
      0,
      3,
      2,
      10,
      9,
      7,
      31,
      26,
      8,
      5,
      19,
      21,
      23,
      18,
      22,
      20,
      6,
      4
    ],
    "043c3b06": [
      65,
      11
    ],
    "56c72ac7": [
      1,
      0,
      3,
      2,
      10,
      9,
      7,
      31,
      26,
      8,
      5,
      19,
      21,
      23,
      18,
      22,
      20,
      6,
      4
    ],
    "33a5c5a8": [
      1,
      0,
      3,
      2,
      10,
      9,
      7,
      31,
      26,
      8,
      5,
      19,
      21,
      23,
      18,
      22,
      20,
      6,
      4
    ],
    "2311b70f": [
      1,
      0,
      3,
      2,
      10,
      9,
      7,
      31,
      26,
      8,
      5,
      19,
      21,
      23,
      18,
      22,
      20,
      6,
      4
    ],
    "4486516e": [
      1,
      0,
      3,
      2,
      10,
      9,
      7,
      31,
      26,
      8,
      5,
      19,
      21,
      23,
      18,
      22,
      20,
      6,
      4
    ],
    "6c1a62c7": [
      1,
      0,
      3,
      2,
      10,
      9,
      7,
      31,
      26,
      8,
      5,
      19,
      21,
      23,
      18,
      22,
      20,
      6,
      4
    ],
    "25ee00c0": [
      1,
      0,
      3,
      2,
      10,
      9,
      7,
      31,
      26,
      8,
      5,
      19,
      21,
      23,
      18,
      22,
      20,
      6,
      4
    ],
    "abcfe84a": [
      1,
      0,
      3,
      2,
      10,
      9,
      7,
      31,
      26,
      8,
      5,
      19,
      21,
      23,
      18,
      22,
      20,
      6,
      4
    ],
    "2e7a1212": [
      1,
      0,
      3,
      2,
      10,
      9,
      7,
      31,
      26,
      8,
      5,
      19,
      21,
      23,
      18,
      22,
      20,
      6,
      4
    ],
    "6174dbc8": [
      65,
      11
    ],
    "39091f88": [
      1,
      0,
      3,
      2,
      10,
      9,
      7,
      31,
      26,
      8,
      5,
      19,
      21,
      23,
      18,
      22,
      20,
      6,
      4
    ],
    "d30a2c4c": [
      1,
      0,
      3,
      2,
      10,
      9,
      7,
      31,
      26,
      8,
      5,
      19,
      21,
      23,
      18,
      22,
      20,
      6,
      4
    ],
    "43c529f5": [
      1,
      0,
      3,
      2,
      10,
      9,
      7,
      31,
      26,
      8,
      5,
      19,
      21,
      23,
      18,
      22,
      20,
      6,
      4
    ],
    "2f2cb7ea": [
      1,
      0,
      3,
      2,
      10,
      9,
      7,
      31,
      26,
      8,
      5,
      19,
      21,
      23,
      18,
      22,
      20,
      6,
      4
    ],
    "d3b06164": [
      1,
      0,
      3,
      2,
      10,
      9,
      7,
      31,
      26,
      8,
      5,
      19,
      21,
      23,
      18,
      22,
      20,
      6,
      4
    ],
    "73c3e109": [
      1,
      0,
      3,
      2,
      10,
      9,
      7,
      31,
      26,
      8,
      5,
      19,
      21,
      23,
      18,
      22,
      20,
      6,
      4
    ],
    "0a48c13e": [
      1,
      0,
      3,
      2,
      10,
      9,
      7,
      31,
      26,
      8,
      5,
      19,
      21,
      23,
      18,
      22,
      20,
      6,
      4
    ],
    "022189a1": [
      1,
      0,
      3,
      2,
      10,
      9,
      7,
      31,
      26,
      8,
      5,
      19,
      21,
      23,
      18,
      22,
      20,
      6,
      4
    ],
    "38c980cc": [
      1,
      0,
      3,
      2,
      10,
      9,
      7,
      31,
      26,
      8,
      5,
      19,
      21,
      23,
      18,
      22,
      20,
      6,
      4
    ],
    "d1998744": [
      1,
      0,
      3,
      2,
      10,
      9,
      7,
      31,
      26,
      8,
      5,
      19,
      21,
      23,
      18,
      22,
      20,
      6,
      4
    ],
    "3b723618": [
      1,
      0,
      3,
      2,
      10,
      9,
      7,
      31,
      26,
      8,
      5,
      19,
      21,
      23,
      18,
      22,
      20,
      6,
      4
    ],
    "74d3311a": [
      1,
      0,
      3,
      2,
      10,
      9,
      7,
      31,
      26,
      8,
      5,
      19,
      21,
      23,
      18,
      22,
      20,
      6,
      4
    ],
    "4a88163b": [
      1,
      0,
      3,
      2,
      10,
      9,
      7,
      31,
      26,
      8,
      5,
      19,
      21,
      23,
      18,
      22,
      20,
      6,
      4
    ],
    "3570ce86": [
      1,
      0,
      3,
      2,
      10,
      9,
      7,
      31,
      26,
      8,
      5,
      19,
      21,
      23,
      18,
      22,
      20,
      6,
      4
    ],
    "39a419b2": [
      1,
      0,
      3,
      2,
      10,
      9,
      7,
      31,
      26,
      8,
      5,
      19,
      21,
      23,
      18,
      22,
      20,
      6,
      4
    ],
    "298f952a": [
      1,
      0,
      3,
      2,
      10,
      9,
      7,
      31,
      26,
      8,
      5,
      19,
      21,
      23,
      18,
      22,
      20,
      6,
      4
    ],
    "470ea5bf": [
      1,
      0,
      3,
      2,
      10,
      9,
      7,
      31,
      26,
      8,
      5,
      19,
      21,
      23,
      18,
      22,
      20,
      6,
      4
    ],
    "1ef1b4b4": [
      1,
      0,
      3,
      2,
      10,
      9,
      7,
      31,
      26,
      8,
      5,
      19,
      21,
      23,
      18,
      22,
      20,
      6,
      4
    ],
    "44bb79c2": [
      1,
      0,
      3,
      2,
      10,
      9,
      7,
      31,
      26,
      8,
      5,
      19,
      21,
      23,
      18,
      22,
      20,
      6,
      4
    ],
    "05847d0d": [
      1,
      0,
      3,
      2,
      10,
      9,
      7,
      31,
      26,
      8,
      5,
      19,
      21,
      23,
      18,
      22,
      20,
      6,
      4
    ],
    "5407e24b": [
      1,
      0,
      3,
      2,
      10,
      9,
      7,
      31,
      26,
      8,
      5,
      19,
      21,
      23,
      18,
      22,
      20,
      6,
      4
    ],
    "237c6184": [
      1,
      0,
      3,
      2,
      10,
      9,
      7,
      31,
      26,
      8,
      5,
      19,
      21,
      23,
      18,
      22,
      20,
      6,
      4
    ],
    "d0e584d4": [
      1,
      0,
      3,
      2,
      10,
      9,
      7,
      31,
      26,
      8,
      5,
      19,
      21,
      23,
      18,
      22,
      20,
      6,
      4
    ],
    "ada6ba48": [
      1,
      0,
      3,
      2,
      10,
      9,
      7,
      31,
      26,
      8,
      5,
      19,
      21,
      23,
      18,
      22,
      20,
      6,
      4
    ],
    "6c829abe": [
      1,
      0,
      3,
      2,
      10,
      9,
      7,
      31,
      26,
      8,
      5,
      19,
      21,
      23,
      18,
      22,
      20,
      6,
      4
    ],
    "1cd673e6": [
      1,
      0,
      3,
      2,
      10,
      9,
      7,
      31,
      26,
      8,
      5,
      19,
      21,
      23,
      18,
      22,
      20,
      6,
      4
    ],
    "1d28bff8": [
      1,
      0,
      3,
      2,
      10,
      9,
      7,
      31,
      26,
      8,
      5,
      19,
      21,
      23,
      18,
      22,
      20,
      6,
      4
    ],
    "b6c42828": [
      1,
      0,
      3,
      2,
      10,
      9,
      7,
      31,
      26,
      8,
      5,
      19,
      21,
      23,
      18,
      22,
      20,
      6,
      4
    ],
    "2501cfe7": [
      1,
      0,
      3,
      2,
      10,
      9,
      7,
      31,
      26,
      8,
      5,
      19,
      21,
      23,
      18,
      22,
      20,
      6,
      4
    ],
    "27c5b990": [
      1,
      0,
      3,
      2,
      10,
      9,
      7,
      31,
      26,
      8,
      5,
      19,
      21,
      23,
      18,
      22,
      20,
      6,
      4
    ],
    "15c06ed0": [
      1,
      0,
      3,
      2,
      10,
      9,
      7,
      31,
      26,
      8,
      5,
      19,
      21,
      23,
      18,
      22,
      20,
      6,
      4
    ],
    "0c8e1f61": [
      65,
      11
    ],
    "32fb426c": [
      65,
      11
    ],
    "660be13c": [
      1,
      0,
      3,
      2,
      10,
      9,
      7,
      31,
      26,
      8,
      5,
      19,
      21,
      23,
      18,
      22,
      20,
      6,
      4
    ],
    "137871b5": [
      1,
      0,
      3,
      2,
      10,
      9,
      7,
      31,
      26,
      8,
      5,
      19,
      21,
      23,
      18,
      22,
      20,
      6,
      4
    ],
    "0ece4256": [
      65,
      11
    ],
    "47e7b850": [
      1,
      0,
      3,
      2,
      10,
      9,
      7,
      31,
      26,
      8,
      5,
      19,
      21,
      23,
      18,
      22,
      20,
      6,
      4
    ],
    "7c12175d": [
      1,
      0,
      3,
      2,
      10,
      9,
      7,
      31,
      26,
      8,
      5,
      19,
      21,
      23,
      18,
      22,
      20,
      6,
      4
    ],
    "3634f556": [
      1,
      0,
      3,
      2,
      10,
      9,
      7,
      31,
      26,
      8,
      5,
      19,
      21,
      23,
      18,
      22,
      20,
      6,
      4
    ],
    "2a033734": [
      1,
      0,
      3,
      2,
      10,
      9,
      7,
      31,
      26,
      8,
      5,
      19,
      21,
      23,
      18,
      22,
      20,
      6,
      4
    ],
    "4e1f21d1": [
      1,
      0,
      3,
      2,
      10,
      9,
      7,
      31,
      26,
      8,
      5,
      19,
      21,
      23,
      18,
      22,
      20,
      6,
      4
    ],
    "6bdd20db": [
      1,
      0,
      3,
      2,
      10,
      9,
      7,
      31,
      26,
      8,
      5,
      19,
      21,
      23,
      18,
      22,
      20,
      6,
      4
    ],
    "33f99231": [
      1,
      0,
      3,
      2,
      10,
      9,
      7,
      31,
      26,
      8,
      5,
      19,
      21,
      23,
      18,
      22,
      20,
      6,
      4
    ],
    "2a10b440": [
      1,
      0,
      3,
      2,
      10,
      9,
      7,
      31,
      26,
      8,
      5,
      19,
      21,
      23,
      18,
      22,
      20,
      6,
      4
    ],
    "1a0ec5db": [
      1,
      0,
      3,
      2,
      10,
      9,
      7,
      31,
      26,
      8,
      5,
      19,
      21,
      23,
      18,
      22,
      20,
      6,
      4
    ],
    "7dac2481": [
      1,
      0,
      3,
      2,
      10,
      9,
      7,
      31,
      26,
      8,
      5,
      19,
      21,
      23,
      18,
      22,
      20,
      6,
      4
    ],
    "ad9f4f44": [
      1,
      0,
      3,
      2,
      10,
      9,
      7,
      31,
      26,
      8,
      5,
      19,
      21,
      23,
      18,
      22,
      20,
      6,
      4
    ],
    "664f1784": [
      1,
      0,
      3,
      2,
      10,
      9,
      7,
      31,
      26,
      8,
      5,
      19,
      21,
      23,
      18,
      22,
      20,
      6,
      4
    ],
    "3d23bdc0": [
      1,
      0,
      3,
      2,
      10,
      9,
      7,
      31,
      26,
      8,
      5,
      19,
      21,
      23,
      18,
      22,
      20,
      6,
      4
    ],
    "f857afb2": [
      1,
      0,
      3,
      2,
      10,
      9,
      7,
      31,
      26,
      8,
      5,
      19,
      21,
      23,
      18,
      22,
      20,
      6,
      4
    ],
    "2fd345e6": [
      1,
      0,
      3,
      2,
      10,
      9,
      7,
      31,
      26,
      8,
      5,
      19,
      21,
      23,
      18,
      22,
      20,
      6,
      4
    ],
    "644cdf14": [
      1,
      0,
      3,
      2,
      10,
      9,
      7,
      31,
      26,
      8,
      5,
      19,
      21,
      23,
      18,
      22,
      20,
      6,
      4
    ],
    "7f8e45d6": [
      1,
      0,
      3,
      2,
      10,
      9,
      7,
      31,
      26,
      8,
      5,
      19,
      21,
      23,
      18,
      22,
      20,
      6,
      4
    ],
    "505ef7d2": [
      1,
      0,
      3,
      2,
      10,
      9,
      7,
      31,
      26,
      8,
      5,
      19,
      21,
      23,
      18,
      22,
      20,
      6,
      4
    ],
    "291c1312": [
      1,
      0,
      3,
      2,
      10,
      9,
      7,
      31,
      26,
      8,
      5,
      19,
      21,
      23,
      18,
      22,
      20,
      6,
      4
    ],
    "8bdbbaf8": [
      1,
      0,
      3,
      2,
      10,
      9,
      7,
      31,
      26,
      8,
      5,
      19,
      21,
      23,
      18,
      22,
      20,
      6,
      4
    ],
    "dcec2820": [
      1,
      0,
      3,
      2,
      10,
      9,
      7,
      31,
      26,
      8,
      5,
      19,
      21,
      23,
      18,
      22,
      20,
      6,
      4
    ],
    "4c348092": [
      1,
      0,
      3,
      2,
      10,
      9,
      7,
      31,
      26,
      8,
      5,
      19,
      21,
      23,
      18,
      22,
      20,
      6,
      4
    ],
    "094bcedf": [
      1,
      0,
      3,
      2,
      10,
      9,
      7,
      31,
      26,
      8,
      5,
      19,
      21,
      23,
      18,
      22,
      20,
      6,
      4
    ],
    "8f41aca4": [
      1,
      0,
      3,
      2,
      10,
      9,
      7,
      31,
      26,
      8,
      5,
      19,
      21,
      23,
      18,
      22,
      20,
      6,
      4
    ],
    "64f0455b": [
      1,
      0,
      3,
      2,
      10,
      9,
      7,
      31,
      26,
      8,
      5,
      19,
      21,
      23,
      18,
      22,
      20,
      6,
      4
    ],
    "3bdf3530": [
      1,
      0,
      3,
      2,
      10,
      9,
      7,
      31,
      26,
      8,
      5,
      19,
      21,
      23,
      18,
      22,
      20,
      6,
      4
    ],
    "882ff220": [
      1,
      0,
      3,
      2,
      10,
      9,
      7,
      31,
      26,
      8,
      5,
      19,
      21,
      23,
      18,
      22,
      20,
      6,
      4
    ],
    "da69346c": [
      1,
      0,
      3,
      2,
      10,
      9,
      7,
      31,
      26,
      8,
      5,
      19,
      21,
      23,
      18,
      22,
      20,
      6,
      4
    ],
    "03e12a96": [
      1,
      0,
      3,
      2,
      10,
      9,
      7,
      31,
      26,
      8,
      5,
      19,
      21,
      23,
      18,
      22,
      20,
      6,
      4
    ],
    "300e6593": [
      1,
      0,
      3,
      2,
      10,
      9,
      7,
      31,
      26,
      8,
      5,
      19,
      21,
      23,
      18,
      22,
      20,
      6,
      4
    ],
    "11b8f7fe": [
      1,
      0,
      3,
      2,
      10,
      9,
      7,
      31,
      26,
      8,
      5,
      19,
      21,
      23,
      18,
      22,
      20,
      6,
      4
    ],
    "0cf4df0c": [
      1,
      0,
      3,
      2,
      10,
      9,
      7,
      31,
      26,
      8,
      5,
      19,
      21,
      23,
      18,
      22,
      20,
      6,
      4
    ],
    "57bd8b72": [
      1,
      0,
      3,
      2,
      10,
      9,
      7,
      31,
      26,
      8,
      5,
      19,
      21,
      23,
      18,
      22,
      20,
      6,
      4
    ],
    "776acbda": [
      1,
      0,
      3,
      2,
      10,
      9,
      7,
      31,
      26,
      8,
      5,
      19,
      21,
      23,
      18,
      22,
      20,
      6,
      4
    ],
    "b1d80618": [
      1,
      0,
      3,
      2,
      10,
      9,
      7,
      31,
      26,
      8,
      5,
      19,
      21,
      23,
      18,
      22,
      20,
      6,
      4
    ],
    "36ba26e8": [
      1,
      0,
      3,
      2,
      10,
      9,
      7,
      31,
      26,
      8,
      5,
      19,
      21,
      23,
      18,
      22,
      20,
      6,
      4
    ],
    "0479b6ee": [
      1,
      0,
      3,
      2,
      10,
      9,
      7,
      31,
      26,
      8,
      5,
      19,
      21,
      23,
      18,
      22,
      20,
      6,
      4
    ],
    "592f6c6f": [
      1,
      0,
      3,
      2,
      10,
      9,
      7,
      31,
      26,
      8,
      5,
      19,
      21,
      23,
      18,
      22,
      20,
      6,
      4
    ],
    "0ea55eaf": [
      1,
      0,
      3,
      2,
      10,
      9,
      7,
      31,
      26,
      8,
      5,
      19,
      21,
      23,
      18,
      22,
      20,
      6,
      4
    ],
    "9ccd6faa": [
      1,
      0,
      3,
      2,
      10,
      9,
      7,
      31,
      26,
      8,
      5,
      19,
      21,
      23,
      18,
      22,
      20,
      6,
      4
    ],
    "4e511882": [
      1,
      0,
      3,
      2,
      10,
      9,
      7,
      31,
      26,
      8,
      5,
      19,
      21,
      23,
      18,
      22,
      20,
      6,
      4
    ],
    "a03d4248": [
      1,
      0,
      3,
      2,
      10,
      9,
      7,
      31,
      26,
      8,
      5,
      19,
      21,
      23,
      18,
      22,
      20,
      6,
      4
    ],
    "4f8d30e4": [
      1,
      0,
      3,
      2,
      10,
      9,
      7,
      31,
      26,
      8,
      5,
      19,
      21,
      23,
      18,
      22,
      20,
      6,
      4
    ],
    "d37191b4": [
      1,
      0,
      3,
      2,
      10,
      9,
      7,
      31,
      26,
      8,
      5,
      19,
      21,
      23,
      18,
      22,
      20,
      6,
      4
    ],
    "18ec7420": [
      1,
      0,
      3,
      2,
      10,
      9,
      7,
      31,
      26,
      8,
      5,
      19,
      21,
      23,
      18,
      22,
      20,
      6,
      4
    ],
    "205dee4e": [
      1,
      0,
      3,
      2,
      10,
      9,
      7,
      31,
      26,
      8,
      5,
      19,
      21,
      23,
      18,
      22,
      20,
      6,
      4
    ],
    "40b45240": [
      1,
      0,
      3,
      2,
      10,
      9,
      7,
      31,
      26,
      8,
      5,
      19,
      21,
      23,
      18,
      22,
      20,
      6,
      4
    ],
    "4bd1f586": [
      1,
      0,
      3,
      2,
      10,
      9,
      7,
      31,
      26,
      8,
      5,
      19,
      21,
      23,
      18,
      22,
      20,
      6,
      4
    ],
    "24b4fc82": [
      1,
      0,
      3,
      2,
      10,
      9,
      7,
      31,
      26,
      8,
      5,
      19,
      21,
      23,
      18,
      22,
      20,
      6,
      4
    ],
    "dbdb13a6": [
      1,
      0,
      3,
      2,
      10,
      9,
      7,
      31,
      26,
      8,
      5,
      19,
      21,
      23,
      18,
      22,
      20,
      6,
      4
    ],
    "4ac91d2a": [
      1,
      0,
      3,
      2,
      10,
      9,
      7,
      31,
      26,
      8,
      5,
      19,
      21,
      23,
      18,
      22,
      20,
      6,
      4
    ],
    "4fb673be": [
      1,
      0,
      3,
      2,
      10,
      9,
      7,
      31,
      26,
      8,
      5,
      19,
      21,
      23,
      18,
      22,
      20,
      6,
      4
    ],
    "6b8d8ed8": [
      1,
      0,
      3,
      2,
      10,
      9,
      7,
      31,
      26,
      8,
      5,
      19,
      21,
      23,
      18,
      22,
      20,
      6,
      4
    ],
    "113bd010": [
      1,
      0,
      3,
      2,
      10,
      9,
      7,
      31,
      26,
      8,
      5,
      19,
      21,
      23,
      18,
      22,
      20,
      6,
      4
    ],
    "1b0421f8": [
      1,
      0,
      3,
      2,
      10,
      9,
      7,
      31,
      26,
      8,
      5,
      19,
      21,
      23,
      18,
      22,
      20,
      6,
      4
    ],
    "d9526b54": [
      1,
      0,
      3,
      2,
      10,
      9,
      7,
      31,
      26,
      8,
      5,
      19,
      21,
      23,
      18,
      22,
      20,
      6,
      4
    ],
    "811be530": [
      1,
      0,
      3,
      2,
      10,
      9,
      7,
      31,
      26,
      8,
      5,
      19,
      21,
      23,
      18,
      22,
      20,
      6,
      4
    ],
    "6b19a5a6": [
      1,
      0,
      3,
      2,
      10,
      9,
      7,
      31,
      26,
      8,
      5,
      19,
      21,
      23,
      18,
      22,
      20,
      6,
      4
    ],
    "65cdfb52": [
      1,
      0,
      3,
      2,
      10,
      9,
      7,
      31,
      26,
      8,
      5,
      19,
      21,
      23,
      18,
      22,
      20,
      6,
      4
    ],
    "e582fdfe": [
      65,
      11
    ],
    "6bdae88c": [
      1,
      0,
      3,
      2,
      10,
      9,
      7,
      31,
      26,
      8,
      5,
      19,
      21,
      23,
      18,
      22,
      20,
      6,
      4
    ],
    "2a28e4f8": [
      1,
      0,
      3,
      2,
      10,
      9,
      7,
      31,
      26,
      8,
      5,
      19,
      21,
      23,
      18,
      22,
      20,
      6,
      4
    ],
    "5be9cace": [
      1,
      0,
      3,
      2,
      10,
      9,
      7,
      31,
      26,
      8,
      5,
      19,
      21,
      23,
      18,
      22,
      20,
      6,
      4
    ],
    "ae94cf86": [
      1,
      0,
      3,
      2,
      10,
      9,
      7,
      31,
      26,
      8,
      5,
      19,
      21,
      23,
      18,
      22,
      20,
      6,
      4
    ],
    "0637bb1b": [
      1,
      0,
      3,
      2,
      10,
      9,
      7,
      31,
      26,
      8,
      5,
      19,
      21,
      23,
      18,
      22,
      20,
      6,
      4
    ],
    "4a760126": [
      1,
      0,
      3,
      2,
      10,
      9,
      7,
      31,
      26,
      8,
      5,
      19,
      21,
      23,
      18,
      22,
      20,
      6,
      4
    ],
    "ba08302c": [
      1,
      0,
      3,
      2,
      10,
      9,
      7,
      31,
      26,
      8,
      5,
      19,
      21,
      23,
      18,
      22,
      20,
      6,
      4
    ],
    "3ff71f7c": [
      1,
      0,
      3,
      2,
      10,
      9,
      7,
      31,
      26,
      8,
      5,
      19,
      21,
      23,
      18,
      22,
      20,
      6,
      4
    ],
    "39428c66": [
      1,
      0,
      3,
      2,
      10,
      9,
      7,
      31,
      26,
      8,
      5,
      19,
      21,
      23,
      18,
      22,
      20,
      6,
      4
    ],
    "ae23ca08": [
      1,
      0,
      3,
      2,
      10,
      9,
      7,
      31,
      26,
      8,
      5,
      19,
      21,
      23,
      18,
      22,
      20,
      6,
      4
    ],
    "8ee3fba6": [
      1,
      0,
      3,
      2,
      10,
      9,
      7,
      31,
      26,
      8,
      5,
      19,
      21,
      23,
      18,
      22,
      20,
      6,
      4
    ],
    "7b69a855": [
      1,
      0,
      3,
      2,
      10,
      9,
      7,
      31,
      26,
      8,
      5,
      19,
      21,
      23,
      18,
      22,
      20,
      6,
      4
    ],
    "64b8bfc8": [
      1,
      0,
      3,
      2,
      10,
      9,
      7,
      31,
      26,
      8,
      5,
      19,
      21,
      23,
      18,
      22,
      20,
      6,
      4
    ],
    "22317f04": [
      1,
      0,
      3,
      2,
      10,
      9,
      7,
      31,
      26,
      8,
      5,
      19,
      21,
      23,
      18,
      22,
      20,
      6,
      4
    ],
    "5f608a1e": [
      1,
      0,
      3,
      2,
      10,
      9,
      7,
      31,
      26,
      8,
      5,
      19,
      21,
      23,
      18,
      22,
      20,
      6,
      4
    ],
    "59962e11": [
      1,
      0,
      3,
      2,
      10,
      9,
      7,
      31,
      26,
      8,
      5,
      19,
      21,
      23,
      18,
      22,
      20,
      6,
      4
    ],
    "b1b5f684": [
      1,
      0,
      3,
      2,
      10,
      9,
      7,
      31,
      26,
      8,
      5,
      19,
      21,
      23,
      18,
      22,
      20,
      6,
      4
    ],
    "644e7ab2": [
      1,
      0,
      3,
      2,
      10,
      9,
      7,
      31,
      26,
      8,
      5,
      19,
      21,
      23,
      18,
      22,
      20,
      6,
      4
    ],
    "057af342": [
      1,
      0,
      3,
      2,
      10,
      9,
      7,
      31,
      26,
      8,
      5,
      19,
      21,
      23,
      18,
      22,
      20,
      6,
      4
    ],
    "3c8f2de9": [
      1,
      0,
      3,
      2,
      10,
      9,
      7,
      31,
      26,
      8,
      5,
      19,
      21,
      23,
      18,
      22,
      20,
      6,
      4
    ],
    "6ae26e10": [
      1,
      0,
      3,
      2,
      10,
      9,
      7,
      31,
      26,
      8,
      5,
      19,
      21,
      23,
      18,
      22,
      20,
      6,
      4
    ],
    "64af13e8": [
      1,
      0,
      3,
      2,
      10,
      9,
      7,
      31,
      26,
      8,
      5,
      19,
      21,
      23,
      18,
      22,
      20,
      6,
      4
    ],
    "23e569ea": [
      1,
      0,
      3,
      2,
      10,
      9,
      7,
      31,
      26,
      8,
      5,
      19,
      21,
      23,
      18,
      22,
      20,
      6,
      4
    ],
    "893478aa": [
      1,
      0,
      3,
      2,
      10,
      9,
      7,
      31,
      26,
      8,
      5,
      19,
      21,
      23,
      18,
      22,
      20,
      6,
      4
    ],
    "1430163f": [
      1,
      0,
      3,
      2,
      10,
      9,
      7,
      31,
      26,
      8,
      5,
      19,
      21,
      23,
      18,
      22,
      20,
      6,
      4
    ],
    "19dcd7a4": [
      1,
      0,
      3,
      2,
      10,
      9,
      7,
      31,
      26,
      8,
      5,
      19,
      21,
      23,
      18,
      22,
      20,
      6,
      4
    ],
    "56c793f8": [
      1,
      0,
      3,
      2,
      10,
      9,
      7,
      31,
      26,
      8,
      5,
      19,
      21,
      23,
      18,
      22,
      20,
      6,
      4
    ],
    "64d6bf32": [
      1,
      0,
      3,
      2,
      10,
      9,
      7,
      31,
      26,
      8,
      5,
      19,
      21,
      23,
      18,
      22,
      20,
      6,
      4
    ],
    "b842fa76": [
      1,
      0,
      3,
      2,
      10,
      9,
      7,
      31,
      26,
      8,
      5,
      19,
      21,
      23,
      18,
      22,
      20,
      6,
      4
    ],
    "d15e34b2": [
      1,
      0,
      3,
      2,
      10,
      9,
      7,
      31,
      26,
      8,
      5,
      19,
      21,
      23,
      18,
      22,
      20,
      6,
      4
    ],
    "47fef4f4": [
      1,
      0,
      3,
      2,
      10,
      9,
      7,
      31,
      26,
      8,
      5,
      19,
      21,
      23,
      18,
      22,
      20,
      6,
      4
    ],
    "68b185cb": [
      1,
      0,
      3,
      2,
      10,
      9,
      7,
      31,
      26,
      8,
      5,
      19,
      21,
      23,
      18,
      22,
      20,
      6,
      4
    ],
    "6a4f82b2": [
      1,
      0,
      3,
      2,
      10,
      9,
      7,
      31,
      26,
      8,
      5,
      19,
      21,
      23,
      18,
      22,
      20,
      6,
      4
    ],
    "594b21b1": [
      1,
      0,
      3,
      2,
      10,
      9,
      7,
      31,
      26,
      8,
      5,
      19,
      21,
      23,
      18,
      22,
      20,
      6,
      4
    ],
    "69844b6d": [
      1,
      0,
      3,
      2,
      10,
      9,
      7,
      31,
      26,
      8,
      5,
      19,
      21,
      23,
      18,
      22,
      20,
      6,
      4
    ],
    "25552cbb": [
      1,
      0,
      3,
      2,
      10,
      9,
      7,
      31,
      26,
      8,
      5,
      19,
      21,
      23,
      18,
      22,
      20,
      6,
      4
    ],
    "09ebe4e0": [
      1,
      0,
      3,
      2,
      10,
      9,
      7,
      31,
      26,
      8,
      5,
      19,
      21,
      23,
      18,
      22,
      20,
      6,
      4
    ],
    "2843f9e0": [
      1,
      0,
      3,
      2,
      10,
      9,
      7,
      31,
      26,
      8,
      5,
      19,
      21,
      23,
      18,
      22,
      20,
      6,
      4
    ],
    "6c88dc23": [
      1,
      0,
      3,
      2,
      10,
      9,
      7,
      31,
      26,
      8,
      5,
      19,
      21,
      23,
      18,
      22,
      20,
      6,
      4
    ],
    "efffabbe": [
      1,
      0,
      3,
      2,
      10,
      9,
      7,
      31,
      26,
      8,
      5,
      19,
      21,
      23,
      18,
      22,
      20,
      6,
      4
    ],
    "26c3422a": [
      1,
      0,
      3,
      2,
      10,
      9,
      7,
      31,
      26,
      8,
      5,
      19,
      21,
      23,
      18,
      22,
      20,
      6,
      4
    ],
    "b151b54c": [
      12
    ],
    "7933cda4": [
      49
    ],
    "188f3e4a": [
      42
    ],
    "5fa78b66": [
      33
    ],
    "29687dbc": [
      35
    ],
    "5f84dafa": [
      27
    ],
    "6fe16fdc": [
      34
    ],
    "b88ba2de": [
      13
    ],
    "3998d172": [
      32
    ],
    "3ccabec6": [
      28
    ],
    "c6a7a18e": [
      17
    ],
    "4a917d19": [
      24
    ],
    "5f27d38f": [
      16
    ],
    "08ba3809": [
      15
    ],
    "6cf4dec0": [
      43
    ],
    "68f7f5fe": [
      41
    ],
    "1c6ff046": [
      1,
      0,
      3,
      2,
      10,
      9,
      7,
      31,
      26,
      8,
      5,
      19,
      21,
      23,
      18,
      22,
      20,
      6,
      4
    ],
    "2888d1e8": [
      1,
      0,
      3,
      2,
      10,
      9,
      7,
      31,
      26,
      8,
      5,
      19,
      21,
      23,
      18,
      22,
      20,
      6,
      4
    ],
    "35e36ca4": [
      1,
      0,
      3,
      2,
      10,
      9,
      7,
      31,
      26,
      8,
      5,
      19,
      21,
      23,
      18,
      22,
      20,
      6,
      4
    ],
    "976b77e0": [
      1,
      0,
      3,
      2,
      10,
      9,
      7,
      31,
      26,
      8,
      5,
      19,
      21,
      23,
      18,
      22,
      20,
      6,
      4
    ],
    "8d4b681c": [
      1,
      0,
      3,
      2,
      10,
      9,
      7,
      31,
      26,
      8,
      5,
      19,
      21,
      23,
      18,
      22,
      20,
      6,
      4
    ],
    "6a291e58": [
      1,
      0,
      3,
      2,
      10,
      9,
      7,
      31,
      26,
      8,
      5,
      19,
      21,
      23,
      18,
      22,
      20,
      6,
      4
    ],
    "63c92730": [
      1,
      0,
      3,
      2,
      10,
      9,
      7,
      31,
      26,
      8,
      5,
      19,
      21,
      23,
      18,
      22,
      20,
      6,
      4
    ],
    "4aa8018d": [
      1,
      0,
      3,
      2,
      10,
      9,
      7,
      31,
      26,
      8,
      5,
      19,
      21,
      23,
      18,
      22,
      20,
      6,
      4
    ],
    "27a8532f": [
      1,
      0,
      3,
      2,
      10,
      9,
      7,
      31,
      26,
      8,
      5,
      19,
      21,
      23,
      18,
      22,
      20,
      6,
      4
    ],
    "e96ad3ac": [
      1,
      0,
      3,
      2,
      10,
      9,
      7,
      31,
      26,
      8,
      5,
      19,
      21,
      23,
      18,
      22,
      20,
      6,
      4
    ],
    "3c5ddbf1": [
      1,
      0,
      3,
      2,
      10,
      9,
      7,
      31,
      26,
      8,
      5,
      19,
      21,
      23,
      18,
      22,
      20,
      6,
      4
    ],
    "248441df": [
      1,
      0,
      3,
      2,
      10,
      9,
      7,
      31,
      26,
      8,
      5,
      19,
      21,
      23,
      18,
      22,
      20,
      6,
      4
    ],
    "06977358": [
      1,
      0,
      3,
      2,
      10,
      9,
      7,
      31,
      26,
      8,
      5,
      19,
      21,
      23,
      18,
      22,
      20,
      6,
      4
    ],
    "59c4aa62": [
      1,
      0,
      3,
      2,
      10,
      9,
      7,
      31,
      26,
      8,
      5,
      19,
      21,
      23,
      18,
      22,
      20,
      6,
      4
    ],
    "32645bda": [
      1,
      0,
      3,
      2,
      10,
      9,
      7,
      31,
      26,
      8,
      5,
      19,
      21,
      23,
      18,
      22,
      20,
      6,
      4
    ],
    "1198eb16": [
      1,
      0,
      3,
      2,
      10,
      9,
      7,
      31,
      26,
      8,
      5,
      19,
      21,
      23,
      18,
      22,
      20,
      6,
      4
    ],
    "095e62c2": [
      1,
      0,
      3,
      2,
      10,
      9,
      7,
      31,
      26,
      8,
      5,
      19,
      21,
      23,
      18,
      22,
      20,
      6,
      4
    ],
    "6e66671a": [
      1,
      0,
      3,
      2,
      10,
      9,
      7,
      31,
      26,
      8,
      5,
      19,
      21,
      23,
      18,
      22,
      20,
      6,
      4
    ],
    "74113ee9": [
      1,
      0,
      3,
      2,
      10,
      9,
      7,
      31,
      26,
      8,
      5,
      19,
      21,
      23,
      18,
      22,
      20,
      6,
      4
    ],
    "64a66004": [
      1,
      0,
      3,
      2,
      10,
      9,
      7,
      31,
      26,
      8,
      5,
      19,
      21,
      23,
      18,
      22,
      20,
      6,
      4
    ],
    "20c74009": [
      1,
      0,
      3,
      2,
      10,
      9,
      7,
      31,
      26,
      8,
      5,
      19,
      21,
      23,
      18,
      22,
      20,
      6,
      4
    ],
    "7f885e06": [
      1,
      0,
      3,
      2,
      10,
      9,
      7,
      31,
      26,
      8,
      5,
      19,
      21,
      23,
      18,
      22,
      20,
      6,
      4
    ],
    "841b1a3c": [
      1,
      0,
      3,
      2,
      10,
      9,
      7,
      31,
      26,
      8,
      5,
      19,
      21,
      23,
      18,
      22,
      20,
      6,
      4
    ],
    "52be7e64": [
      1,
      0,
      3,
      2,
      10,
      9,
      7,
      31,
      26,
      8,
      5,
      19,
      21,
      23,
      18,
      22,
      20,
      6,
      4
    ],
    "69c85d5e": [
      1,
      0,
      3,
      2,
      10,
      9,
      7,
      31,
      26,
      8,
      5,
      19,
      21,
      23,
      18,
      22,
      20,
      6,
      4
    ],
    "b9097b68": [
      1,
      0,
      3,
      2,
      10,
      9,
      7,
      31,
      26,
      8,
      5,
      19,
      21,
      23,
      18,
      22,
      20,
      6,
      4
    ],
    "0c1d5c2d": [
      1,
      0,
      3,
      2,
      10,
      9,
      7,
      31,
      26,
      8,
      5,
      19,
      21,
      23,
      18,
      22,
      20,
      6,
      4
    ],
    "1ed6bc84": [
      1,
      0,
      3,
      2,
      10,
      9,
      7,
      31,
      26,
      8,
      5,
      19,
      21,
      23,
      18,
      22,
      20,
      6,
      4
    ],
    "48fda925": [
      1,
      0,
      3,
      2,
      10,
      9,
      7,
      31,
      26,
      8,
      5,
      19,
      21,
      23,
      18,
      22,
      20,
      6,
      4
    ],
    "52b657a9": [
      1,
      0,
      3,
      2,
      10,
      9,
      7,
      31,
      26,
      8,
      5,
      19,
      21,
      23,
      18,
      22,
      20,
      6,
      4
    ],
    "26cfe138": [
      1,
      0,
      3,
      2,
      10,
      9,
      7,
      31,
      26,
      8,
      5,
      19,
      21,
      23,
      18,
      22,
      20,
      6,
      4
    ],
    "05ca3f72": [
      1,
      0,
      3,
      2,
      10,
      9,
      7,
      31,
      26,
      8,
      5,
      19,
      21,
      23,
      18,
      22,
      20,
      6,
      4
    ],
    "40d2abf7": [
      1,
      0,
      3,
      2,
      10,
      9,
      7,
      31,
      26,
      8,
      5,
      19,
      21,
      23,
      18,
      22,
      20,
      6,
      4
    ],
    "49d541b2": [
      1,
      0,
      3,
      2,
      10,
      9,
      7,
      31,
      26,
      8,
      5,
      19,
      21,
      23,
      18,
      22,
      20,
      6,
      4
    ],
    "792e2b31": [
      1,
      0,
      3,
      2,
      10,
      9,
      7,
      31,
      26,
      8,
      5,
      19,
      21,
      23,
      18,
      22,
      20,
      6,
      4
    ],
    "68c02872": [
      1,
      0,
      3,
      2,
      10,
      9,
      7,
      31,
      26,
      8,
      5,
      19,
      21,
      23,
      18,
      22,
      20,
      6,
      4
    ],
    "883c5db6": [
      1,
      0,
      3,
      2,
      10,
      9,
      7,
      31,
      26,
      8,
      5,
      19,
      21,
      23,
      18,
      22,
      20,
      6,
      4
    ],
    "1ade5674": [
      1,
      0,
      3,
      2,
      10,
      9,
      7,
      31,
      26,
      8,
      5,
      19,
      21,
      23,
      18,
      22,
      20,
      6,
      4
    ],
    "61e944c2": [
      1,
      0,
      3,
      2,
      10,
      9,
      7,
      31,
      26,
      8,
      5,
      19,
      21,
      23,
      18,
      22,
      20,
      6,
      4
    ],
    "44337cc9": [
      1,
      0,
      3,
      2,
      10,
      9,
      7,
      31,
      26,
      8,
      5,
      19,
      21,
      23,
      18,
      22,
      20,
      6,
      4
    ],
    "5815d53d": [
      1,
      0,
      3,
      2,
      10,
      9,
      7,
      31,
      26,
      8,
      5,
      19,
      21,
      23,
      18,
      22,
      20,
      6,
      4
    ],
    "5c0e1024": [
      1,
      0,
      3,
      2,
      10,
      9,
      7,
      31,
      26,
      8,
      5,
      19,
      21,
      23,
      18,
      22,
      20,
      6,
      4
    ],
    "4e1be786": [
      1,
      0,
      3,
      2,
      10,
      9,
      7,
      31,
      26,
      8,
      5,
      19,
      21,
      23,
      18,
      22,
      20,
      6,
      4
    ],
    "8011bcf6": [
      1,
      0,
      3,
      2,
      10,
      9,
      7,
      31,
      26,
      8,
      5,
      19,
      21,
      23,
      18,
      22,
      20,
      6,
      4
    ],
    "a59d9b28": [
      1,
      0,
      3,
      2,
      10,
      9,
      7,
      31,
      26,
      8,
      5,
      19,
      21,
      23,
      18,
      22,
      20,
      6,
      4
    ],
    "534b323c": [
      1,
      0,
      3,
      2,
      10,
      9,
      7,
      31,
      26,
      8,
      5,
      19,
      21,
      23,
      18,
      22,
      20,
      6,
      4
    ],
    "69d91eb3": [
      1,
      0,
      3,
      2,
      10,
      9,
      7,
      31,
      26,
      8,
      5,
      19,
      21,
      23,
      18,
      22,
      20,
      6,
      4
    ],
    "720a5b7a": [
      1,
      0,
      3,
      2,
      10,
      9,
      7,
      31,
      26,
      8,
      5,
      19,
      21,
      23,
      18,
      22,
      20,
      6,
      4
    ],
    "444dce15": [
      1,
      0,
      3,
      2,
      10,
      9,
      7,
      31,
      26,
      8,
      5,
      19,
      21,
      23,
      18,
      22,
      20,
      6,
      4
    ],
    "69163f35": [
      1,
      0,
      3,
      2,
      10,
      9,
      7,
      31,
      26,
      8,
      5,
      19,
      21,
      23,
      18,
      22,
      20,
      6,
      4
    ],
    "9f35733c": [
      1,
      0,
      3,
      2,
      10,
      9,
      7,
      31,
      26,
      8,
      5,
      19,
      21,
      23,
      18,
      22,
      20,
      6,
      4
    ],
    "3a7fcdc5": [
      1,
      0,
      3,
      2,
      10,
      9,
      7,
      31,
      26,
      8,
      5,
      19,
      21,
      23,
      18,
      22,
      20,
      6,
      4
    ],
    "786c18c6": [
      1,
      0,
      3,
      2,
      10,
      9,
      7,
      31,
      26,
      8,
      5,
      19,
      21,
      23,
      18,
      22,
      20,
      6,
      4
    ],
    "3855a632": [
      1,
      0,
      3,
      2,
      10,
      9,
      7,
      31,
      26,
      8,
      5,
      19,
      21,
      23,
      18,
      22,
      20,
      6,
      4
    ],
    "73eda950": [
      1,
      0,
      3,
      2,
      10,
      9,
      7,
      31,
      26,
      8,
      5,
      19,
      21,
      23,
      18,
      22,
      20,
      6,
      4
    ],
    "429bd61e": [
      1,
      0,
      3,
      2,
      10,
      9,
      7,
      31,
      26,
      8,
      5,
      19,
      21,
      23,
      18,
      22,
      20,
      6,
      4
    ],
    "1a648b53": [
      1,
      0,
      3,
      2,
      10,
      9,
      7,
      31,
      26,
      8,
      5,
      19,
      21,
      23,
      18,
      22,
      20,
      6,
      4
    ],
    "f32f6530": [
      1,
      0,
      3,
      2,
      10,
      9,
      7,
      31,
      26,
      8,
      5,
      19,
      21,
      23,
      18,
      22,
      20,
      6,
      4
    ],
    "6d0b1f30": [
      12
    ],
    "e63dd00e": [
      1,
      0,
      3,
      2,
      10,
      9,
      7,
      31,
      26,
      8,
      5,
      19,
      21,
      23,
      18,
      22,
      20,
      6,
      4
    ],
    "05ed031a": [
      1,
      0,
      3,
      2,
      10,
      9,
      7,
      31,
      26,
      8,
      5,
      19,
      21,
      23,
      18,
      22,
      20,
      6,
      4
    ],
    "1e13081e": [
      1,
      0,
      3,
      2,
      10,
      9,
      7,
      31,
      26,
      8,
      5,
      19,
      21,
      23,
      18,
      22,
      20,
      6,
      4
    ],
    "130bb1f6": [
      1,
      0,
      3,
      2,
      10,
      9,
      7,
      31,
      26,
      8,
      5,
      19,
      21,
      23,
      18,
      22,
      20,
      6,
      4
    ],
    "13b32e51": [
      1,
      0,
      3,
      2,
      10,
      9,
      7,
      31,
      26,
      8,
      5,
      19,
      21,
      23,
      18,
      22,
      20,
      6,
      4
    ],
    "612d8e83": [
      1,
      0,
      3,
      2,
      10,
      9,
      7,
      31,
      26,
      8,
      5,
      19,
      21,
      23,
      18,
      22,
      20,
      6,
      4
    ],
    "0809e0ab": [
      1,
      0,
      3,
      2,
      10,
      9,
      7,
      31,
      26,
      8,
      5,
      19,
      21,
      23,
      18,
      22,
      20,
      6,
      4
    ],
    "0817e0f6": [
      1,
      0,
      3,
      2,
      10,
      9,
      7,
      31,
      26,
      8,
      5,
      19,
      21,
      23,
      18,
      22,
      20,
      6,
      4
    ],
    "5ac8e588": [
      1,
      0,
      3,
      2,
      10,
      9,
      7,
      31,
      26,
      8,
      5,
      19,
      21,
      23,
      18,
      22,
      20,
      6,
      4
    ],
    "9446801a": [
      1,
      0,
      3,
      2,
      10,
      9,
      7,
      31,
      26,
      8,
      5,
      19,
      21,
      23,
      18,
      22,
      20,
      6,
      4
    ],
    "45e5b2a7": [
      1,
      0,
      3,
      2,
      10,
      9,
      7,
      31,
      26,
      8,
      5,
      19,
      21,
      23,
      18,
      22,
      20,
      6,
      4
    ],
    "9fea051e": [
      1,
      0,
      3,
      2,
      10,
      9,
      7,
      31,
      26,
      8,
      5,
      19,
      21,
      23,
      18,
      22,
      20,
      6,
      4
    ],
    "a8907d84": [
      1,
      0,
      3,
      2,
      10,
      9,
      7,
      31,
      26,
      8,
      5,
      19,
      21,
      23,
      18,
      22,
      20,
      6,
      4
    ],
    "196c80d7": [
      1,
      0,
      3,
      2,
      10,
      9,
      7,
      31,
      26,
      8,
      5,
      19,
      21,
      23,
      18,
      22,
      20,
      6,
      4
    ],
    "2e6ea82f": [
      1,
      0,
      3,
      2,
      10,
      9,
      7,
      31,
      26,
      8,
      5,
      19,
      21,
      23,
      18,
      22,
      20,
      6,
      4
    ],
    "d21b6eb8": [
      49
    ],
    "7f8837d3": [
      49
    ],
    "12c18daf": [
      1,
      0,
      3,
      2,
      10,
      9,
      7,
      31,
      26,
      8,
      5,
      19,
      21,
      23,
      18,
      22,
      20,
      6,
      4
    ],
    "1d316d8a": [
      42
    ],
    "c4db9ade": [
      42
    ],
    "65203f8e": [
      33
    ],
    "f5e362c8": [
      33
    ],
    "6f16a1d0": [
      1,
      0,
      3,
      2,
      10,
      9,
      7,
      31,
      26,
      8,
      5,
      19,
      21,
      23,
      18,
      22,
      20,
      6,
      4
    ],
    "44d7c657": [
      35
    ],
    "05c5e5b2": [
      35
    ],
    "0c7f668d": [
      1,
      0,
      3,
      2,
      10,
      9,
      7,
      31,
      26,
      8,
      5,
      19,
      21,
      23,
      18,
      22,
      20,
      6,
      4
    ],
    "4bc2f7f0": [
      1,
      0,
      3,
      2,
      10,
      9,
      7,
      31,
      26,
      8,
      5,
      19,
      21,
      23,
      18,
      22,
      20,
      6,
      4
    ],
    "19a760c2": [
      27
    ],
    "7cf1b831": [
      1,
      0,
      3,
      2,
      10,
      9,
      7,
      31,
      26,
      8,
      5,
      19,
      21,
      23,
      18,
      22,
      20,
      6,
      4
    ],
    "b54e9ef4": [
      34
    ],
    "2bdc19c8": [
      34
    ],
    "4ea77644": [
      1,
      0,
      3,
      2,
      10,
      9,
      7,
      31,
      26,
      8,
      5,
      19,
      21,
      23,
      18,
      22,
      20,
      6,
      4
    ],
    "3cfdbcc5": [
      1,
      0,
      3,
      2,
      10,
      9,
      7,
      31,
      26,
      8,
      5,
      19,
      21,
      23,
      18,
      22,
      20,
      6,
      4
    ],
    "cd91399e": [
      1,
      0,
      3,
      2,
      10,
      9,
      7,
      31,
      26,
      8,
      5,
      19,
      21,
      23,
      18,
      22,
      20,
      6,
      4
    ],
    "59e979e0": [
      1,
      0,
      3,
      2,
      10,
      9,
      7,
      31,
      26,
      8,
      5,
      19,
      21,
      23,
      18,
      22,
      20,
      6,
      4
    ],
    "0b6d83d5": [
      1,
      0,
      3,
      2,
      10,
      9,
      7,
      31,
      26,
      8,
      5,
      19,
      21,
      23,
      18,
      22,
      20,
      6,
      4
    ],
    "3a12c006": [
      1,
      0,
      3,
      2,
      10,
      9,
      7,
      31,
      26,
      8,
      5,
      19,
      21,
      23,
      18,
      22,
      20,
      6,
      4
    ],
    "36d24156": [
      1,
      0,
      3,
      2,
      10,
      9,
      7,
      31,
      26,
      8,
      5,
      19,
      21,
      23,
      18,
      22,
      20,
      6,
      4
    ],
    "7ecb8c30": [
      32
    ],
    "0d94e173": [
      32
    ],
    "eca7162e": [
      1,
      0,
      3,
      2,
      10,
      9,
      7,
      31,
      26,
      8,
      5,
      19,
      21,
      23,
      18,
      22,
      20,
      6,
      4
    ],
    "9bda82f4": [
      28
    ],
    "3d88875a": [
      1,
      0,
      3,
      2,
      10,
      9,
      7,
      31,
      26,
      8,
      5,
      19,
      21,
      23,
      18,
      22,
      20,
      6,
      4
    ],
    "4fe219a9": [
      17
    ],
    "0f40baac": [
      1,
      0,
      3,
      2,
      10,
      9,
      7,
      31,
      26,
      8,
      5,
      19,
      21,
      23,
      18,
      22,
      20,
      6,
      4
    ],
    "01e599e4": [
      1,
      0,
      3,
      2,
      10,
      9,
      7,
      31,
      26,
      8,
      5,
      19,
      21,
      23,
      18,
      22,
      20,
      6,
      4
    ],
    "b5900e92": [
      1,
      0,
      3,
      2,
      10,
      9,
      7,
      31,
      26,
      8,
      5,
      19,
      21,
      23,
      18,
      22,
      20,
      6,
      4
    ],
    "2526be89": [
      24
    ],
    "6ae4a453": [
      16
    ],
    "872f00ba": [
      15
    ],
    "561b95a3": [
      43
    ],
    "f6f4e428": [
      43
    ],
    "7ba34bb5": [
      41
    ],
    "4447e9ad": [
      41
    ],
    "49ba9698": [
      1,
      0,
      3,
      2,
      10,
      9,
      7,
      31,
      26,
      8,
      5,
      19,
      21,
      23,
      18,
      22,
      20,
      6,
      4
    ],
    "92d8872a": [
      1,
      0,
      3,
      2,
      10,
      9,
      7,
      31,
      26,
      8,
      5,
      19,
      21,
      23,
      18,
      22,
      20,
      6,
      4
    ],
    "bab4c4ee": [
      1,
      0,
      3,
      2,
      10,
      9,
      7,
      31,
      26,
      8,
      5,
      19,
      21,
      23,
      18,
      22,
      20,
      6,
      4
    ],
    "10fd496c": [
      1,
      0,
      3,
      2,
      10,
      9,
      7,
      31,
      26,
      8,
      5,
      19,
      21,
      23,
      18,
      22,
      20,
      6,
      4
    ],
    "5f173e28": [
      1,
      0,
      3,
      2,
      10,
      9,
      7,
      31,
      26,
      8,
      5,
      19,
      21,
      23,
      18,
      22,
      20,
      6,
      4
    ],
    "52741ee5": [
      1,
      0,
      3,
      2,
      10,
      9,
      7,
      31,
      26,
      8,
      5,
      19,
      21,
      23,
      18,
      22,
      20,
      6,
      4
    ],
    "1f644290": [
      1,
      0,
      3,
      2,
      10,
      9,
      7,
      31,
      26,
      8,
      5,
      19,
      21,
      23,
      18,
      22,
      20,
      6,
      4
    ],
    "d72af6a4": [
      1,
      0,
      3,
      2,
      10,
      9,
      7,
      31,
      26,
      8,
      5,
      19,
      21,
      23,
      18,
      22,
      20,
      6,
      4
    ],
    "e8b654bc": [
      1,
      0,
      3,
      2,
      10,
      9,
      7,
      31,
      26,
      8,
      5,
      19,
      21,
      23,
      18,
      22,
      20,
      6,
      4
    ],
    "2b2cb0b5": [
      1,
      0,
      3,
      2,
      10,
      9,
      7,
      31,
      26,
      8,
      5,
      19,
      21,
      23,
      18,
      22,
      20,
      6,
      4
    ],
    "fd5fc394": [
      1,
      0,
      3,
      2,
      10,
      9,
      7,
      31,
      26,
      8,
      5,
      19,
      21,
      23,
      18,
      22,
      20,
      6,
      4
    ],
    "c7d01158": [
      1,
      0,
      3,
      2,
      10,
      9,
      7,
      31,
      26,
      8,
      5,
      19,
      21,
      23,
      18,
      22,
      20,
      6,
      4
    ],
    "4834b212": [
      1,
      0,
      3,
      2,
      10,
      9,
      7,
      31,
      26,
      8,
      5,
      19,
      21,
      23,
      18,
      22,
      20,
      6,
      4
    ],
    "33f17c0a": [
      1,
      0,
      3,
      2,
      10,
      9,
      7,
      31,
      26,
      8,
      5,
      19,
      21,
      23,
      18,
      22,
      20,
      6,
      4
    ],
    "774768f2": [
      1,
      0,
      3,
      2,
      10,
      9,
      7,
      31,
      26,
      8,
      5,
      19,
      21,
      23,
      18,
      22,
      20,
      6,
      4
    ],
    "113f1984": [
      1,
      0,
      3,
      2,
      10,
      9,
      7,
      31,
      26,
      8,
      5,
      19,
      21,
      23,
      18,
      22,
      20,
      6,
      4
    ],
    "3f7190cb": [
      1,
      0,
      3,
      2,
      10,
      9,
      7,
      31,
      26,
      8,
      5,
      19,
      21,
      23,
      18,
      22,
      20,
      6,
      4
    ],
    "3f1c4c42": [
      1,
      0,
      3,
      2,
      10,
      9,
      7,
      31,
      26,
      8,
      5,
      19,
      21,
      23,
      18,
      22,
      20,
      6,
      4
    ],
    "1acd4490": [
      1,
      0,
      3,
      2,
      10,
      9,
      7,
      31,
      26,
      8,
      5,
      19,
      21,
      23,
      18,
      22,
      20,
      6,
      4
    ],
    "34937ac2": [
      1,
      0,
      3,
      2,
      10,
      9,
      7,
      31,
      26,
      8,
      5,
      19,
      21,
      23,
      18,
      22,
      20,
      6,
      4
    ],
    "a06fdfd4": [
      1,
      0,
      3,
      2,
      10,
      9,
      7,
      31,
      26,
      8,
      5,
      19,
      21,
      23,
      18,
      22,
      20,
      6,
      4
    ],
    "78b3c569": [
      1,
      0,
      3,
      2,
      10,
      9,
      7,
      31,
      26,
      8,
      5,
      19,
      21,
      23,
      18,
      22,
      20,
      6,
      4
    ],
    "2e117fee": [
      1,
      0,
      3,
      2,
      10,
      9,
      7,
      31,
      26,
      8,
      5,
      19,
      21,
      23,
      18,
      22,
      20,
      6,
      4
    ],
    "21c5ba70": [
      12
    ],
    "fc26d9b8": [
      1,
      0,
      3,
      2,
      10,
      9,
      7,
      31,
      26,
      8,
      5,
      19,
      21,
      23,
      18,
      22,
      20,
      6,
      4
    ],
    "ec294778": [
      1,
      0,
      3,
      2,
      10,
      9,
      7,
      31,
      26,
      8,
      5,
      19,
      21,
      23,
      18,
      22,
      20,
      6,
      4
    ],
    "148b6630": [
      1,
      0,
      3,
      2,
      10,
      9,
      7,
      31,
      26,
      8,
      5,
      19,
      21,
      23,
      18,
      22,
      20,
      6,
      4
    ],
    "1ad0d59e": [
      1,
      0,
      3,
      2,
      10,
      9,
      7,
      31,
      26,
      8,
      5,
      19,
      21,
      23,
      18,
      22,
      20,
      6,
      4
    ],
    "146142df": [
      1,
      0,
      3,
      2,
      10,
      9,
      7,
      31,
      26,
      8,
      5,
      19,
      21,
      23,
      18,
      22,
      20,
      6,
      4
    ],
    "b8f3fa10": [
      1,
      0,
      3,
      2,
      10,
      9,
      7,
      31,
      26,
      8,
      5,
      19,
      21,
      23,
      18,
      22,
      20,
      6,
      4
    ],
    "c4989b78": [
      49
    ],
    "745b9b9b": [
      42
    ],
    "8a3cf79e": [
      42
    ],
    "612c6299": [
      33
    ],
    "6d07703c": [
      33
    ],
    "7d9a76ac": [
      1,
      0,
      3,
      2,
      10,
      9,
      7,
      31,
      26,
      8,
      5,
      19,
      21,
      23,
      18,
      22,
      20,
      6,
      4
    ],
    "49059e92": [
      35
    ],
    "5805c15c": [
      35
    ],
    "6d664b42": [
      1,
      0,
      3,
      2,
      10,
      9,
      7,
      31,
      26,
      8,
      5,
      19,
      21,
      23,
      18,
      22,
      20,
      6,
      4
    ],
    "703f5c21": [
      1,
      0,
      3,
      2,
      10,
      9,
      7,
      31,
      26,
      8,
      5,
      19,
      21,
      23,
      18,
      22,
      20,
      6,
      4
    ],
    "8b5f0a20": [
      1,
      0,
      3,
      2,
      10,
      9,
      7,
      31,
      26,
      8,
      5,
      19,
      21,
      23,
      18,
      22,
      20,
      6,
      4
    ],
    "51bfa792": [
      1,
      0,
      3,
      2,
      10,
      9,
      7,
      31,
      26,
      8,
      5,
      19,
      21,
      23,
      18,
      22,
      20,
      6,
      4
    ],
    "f4b2bc02": [
      27
    ],
    "fe22abb4": [
      34
    ],
    "8f1207b0": [
      34
    ],
    "08dbd1f1": [
      13
    ],
    "3fc7cab8": [
      1,
      0,
      3,
      2,
      10,
      9,
      7,
      31,
      26,
      8,
      5,
      19,
      21,
      23,
      18,
      22,
      20,
      6,
      4
    ],
    "87d4b7de": [
      1,
      0,
      3,
      2,
      10,
      9,
      7,
      31,
      26,
      8,
      5,
      19,
      21,
      23,
      18,
      22,
      20,
      6,
      4
    ],
    "314919b5": [
      1,
      0,
      3,
      2,
      10,
      9,
      7,
      31,
      26,
      8,
      5,
      19,
      21,
      23,
      18,
      22,
      20,
      6,
      4
    ],
    "2561a00f": [
      1,
      0,
      3,
      2,
      10,
      9,
      7,
      31,
      26,
      8,
      5,
      19,
      21,
      23,
      18,
      22,
      20,
      6,
      4
    ],
    "0c18690a": [
      1,
      0,
      3,
      2,
      10,
      9,
      7,
      31,
      26,
      8,
      5,
      19,
      21,
      23,
      18,
      22,
      20,
      6,
      4
    ],
    "1af4c6e2": [
      1,
      0,
      3,
      2,
      10,
      9,
      7,
      31,
      26,
      8,
      5,
      19,
      21,
      23,
      18,
      22,
      20,
      6,
      4
    ],
    "0e984b88": [
      32
    ],
    "41fea85a": [
      32
    ],
    "2d0ce826": [
      28
    ],
    "c3a787ee": [
      17
    ],
    "0255f8e9": [
      24
    ],
    "4813deb3": [
      16
    ],
    "f5bedd7a": [
      15
    ],
    "b7ccb17a": [
      43
    ],
    "55f1584c": [
      43
    ],
    "d4126556": [
      41
    ],
    "d76f77e6": [
      41
    ],
    "6540307b": [
      1,
      0,
      3,
      2,
      10,
      9,
      7,
      31,
      26,
      8,
      5,
      19,
      21,
      23,
      18,
      22,
      20,
      6,
      4
    ],
    "5bfb256f": [
      1,
      0,
      3,
      2,
      10,
      9,
      7,
      31,
      26,
      8,
      5,
      19,
      21,
      23,
      18,
      22,
      20,
      6,
      4
    ],
    "5387e1fc": [
      1,
      0,
      3,
      2,
      10,
      9,
      7,
      31,
      26,
      8,
      5,
      19,
      21,
      23,
      18,
      22,
      20,
      6,
      4
    ],
    "ade7a9d2": [
      1,
      0,
      3,
      2,
      10,
      9,
      7,
      31,
      26,
      8,
      5,
      19,
      21,
      23,
      18,
      22,
      20,
      6,
      4
    ],
    "f40a8c14": [
      1,
      0,
      3,
      2,
      10,
      9,
      7,
      31,
      26,
      8,
      5,
      19,
      21,
      23,
      18,
      22,
      20,
      6,
      4
    ],
    "7b5d9b05": [
      1,
      0,
      3,
      2,
      10,
      9,
      7,
      31,
      26,
      8,
      5,
      19,
      21,
      23,
      18,
      22,
      20,
      6,
      4
    ],
    "37d5e464": [
      1,
      0,
      3,
      2,
      10,
      9,
      7,
      31,
      26,
      8,
      5,
      19,
      21,
      23,
      18,
      22,
      20,
      6,
      4
    ],
    "39bcc8bc": [
      1,
      0,
      3,
      2,
      10,
      9,
      7,
      31,
      26,
      8,
      5,
      19,
      21,
      23,
      18,
      22,
      20,
      6,
      4
    ],
    "278ceb62": [
      1,
      0,
      3,
      2,
      10,
      9,
      7,
      31,
      26,
      8,
      5,
      19,
      21,
      23,
      18,
      22,
      20,
      6,
      4
    ],
    "551717a4": [
      1,
      0,
      3,
      2,
      10,
      9,
      7,
      31,
      26,
      8,
      5,
      19,
      21,
      23,
      18,
      22,
      20,
      6,
      4
    ],
    "72335aee": [
      1,
      0,
      3,
      2,
      10,
      9,
      7,
      31,
      26,
      8,
      5,
      19,
      21,
      23,
      18,
      22,
      20,
      6,
      4
    ],
    "e8060a0e": [
      1,
      0,
      3,
      2,
      10,
      9,
      7,
      31,
      26,
      8,
      5,
      19,
      21,
      23,
      18,
      22,
      20,
      6,
      4
    ],
    "479bc504": [
      1,
      0,
      3,
      2,
      10,
      9,
      7,
      31,
      26,
      8,
      5,
      19,
      21,
      23,
      18,
      22,
      20,
      6,
      4
    ],
    "eb188448": [
      1,
      0,
      3,
      2,
      10,
      9,
      7,
      31,
      26,
      8,
      5,
      19,
      21,
      23,
      18,
      22,
      20,
      6,
      4
    ],
    "21b5981c": [
      1,
      0,
      3,
      2,
      10,
      9,
      7,
      31,
      26,
      8,
      5,
      19,
      21,
      23,
      18,
      22,
      20,
      6,
      4
    ],
    "83828aa0": [
      1,
      0,
      3,
      2,
      10,
      9,
      7,
      31,
      26,
      8,
      5,
      19,
      21,
      23,
      18,
      22,
      20,
      6,
      4
    ],
    "7261fd10": [
      1,
      0,
      3,
      2,
      10,
      9,
      7,
      31,
      26,
      8,
      5,
      19,
      21,
      23,
      18,
      22,
      20,
      6,
      4
    ],
    "49e28133": [
      1,
      0,
      3,
      2,
      10,
      9,
      7,
      31,
      26,
      8,
      5,
      19,
      21,
      23,
      18,
      22,
      20,
      6,
      4
    ],
    "66a06b74": [
      1,
      0,
      3,
      2,
      10,
      9,
      7,
      31,
      26,
      8,
      5,
      19,
      21,
      23,
      18,
      22,
      20,
      6,
      4
    ],
    "3f9f3de2": [
      1,
      0,
      3,
      2,
      10,
      9,
      7,
      31,
      26,
      8,
      5,
      19,
      21,
      23,
      18,
      22,
      20,
      6,
      4
    ],
    "212c130c": [
      1,
      0,
      3,
      2,
      10,
      9,
      7,
      31,
      26,
      8,
      5,
      19,
      21,
      23,
      18,
      22,
      20,
      6,
      4
    ],
    "418284d8": [
      1,
      0,
      3,
      2,
      10,
      9,
      7,
      31,
      26,
      8,
      5,
      19,
      21,
      23,
      18,
      22,
      20,
      6,
      4
    ],
    "9384f894": [
      1,
      0,
      3,
      2,
      10,
      9,
      7,
      31,
      26,
      8,
      5,
      19,
      21,
      23,
      18,
      22,
      20,
      6,
      4
    ],
    "48c1ecb2": [
      1,
      0,
      3,
      2,
      10,
      9,
      7,
      31,
      26,
      8,
      5,
      19,
      21,
      23,
      18,
      22,
      20,
      6,
      4
    ],
    "a573c11c": [
      1,
      0,
      3,
      2,
      10,
      9,
      7,
      31,
      26,
      8,
      5,
      19,
      21,
      23,
      18,
      22,
      20,
      6,
      4
    ],
    "33e7ac28": [
      1,
      0,
      3,
      2,
      10,
      9,
      7,
      31,
      26,
      8,
      5,
      19,
      21,
      23,
      18,
      22,
      20,
      6,
      4
    ],
    "5790be78": [
      1,
      0,
      3,
      2,
      10,
      9,
      7,
      31,
      26,
      8,
      5,
      19,
      21,
      23,
      18,
      22,
      20,
      6,
      4
    ],
    "f8ffaf86": [
      1,
      0,
      3,
      2,
      10,
      9,
      7,
      31,
      26,
      8,
      5,
      19,
      21,
      23,
      18,
      22,
      20,
      6,
      4
    ],
    "a228b0a8": [
      1,
      0,
      3,
      2,
      10,
      9,
      7,
      31,
      26,
      8,
      5,
      19,
      21,
      23,
      18,
      22,
      20,
      6,
      4
    ],
    "1b4f1b2f": [
      1,
      0,
      3,
      2,
      10,
      9,
      7,
      31,
      26,
      8,
      5,
      19,
      21,
      23,
      18,
      22,
      20,
      6,
      4
    ],
    "e8b3e1fc": [
      1,
      0,
      3,
      2,
      10,
      9,
      7,
      31,
      26,
      8,
      5,
      19,
      21,
      23,
      18,
      22,
      20,
      6,
      4
    ],
    "70778bc8": [
      1,
      0,
      3,
      2,
      10,
      9,
      7,
      31,
      26,
      8,
      5,
      19,
      21,
      23,
      18,
      22,
      20,
      6,
      4
    ],
    "5e8dfab5": [
      1,
      0,
      3,
      2,
      10,
      9,
      7,
      31,
      26,
      8,
      5,
      19,
      21,
      23,
      18,
      22,
      20,
      6,
      4
    ],
    "8843e7cc": [
      1,
      0,
      3,
      2,
      10,
      9,
      7,
      31,
      26,
      8,
      5,
      19,
      21,
      23,
      18,
      22,
      20,
      6,
      4
    ],
    "4dbe59de": [
      1,
      0,
      3,
      2,
      10,
      9,
      7,
      31,
      26,
      8,
      5,
      19,
      21,
      23,
      18,
      22,
      20,
      6,
      4
    ],
    "ac6c96d6": [
      1,
      0,
      3,
      2,
      10,
      9,
      7,
      31,
      26,
      8,
      5,
      19,
      21,
      23,
      18,
      22,
      20,
      6,
      4
    ],
    "7b4e4735": [
      1,
      0,
      3,
      2,
      10,
      9,
      7,
      31,
      26,
      8,
      5,
      19,
      21,
      23,
      18,
      22,
      20,
      6,
      4
    ],
    "7d6bb493": [
      1,
      0,
      3,
      2,
      10,
      9,
      7,
      31,
      26,
      8,
      5,
      19,
      21,
      23,
      18,
      22,
      20,
      6,
      4
    ],
    "89b03d9c": [
      1,
      0,
      3,
      2,
      10,
      9,
      7,
      31,
      26,
      8,
      5,
      19,
      21,
      23,
      18,
      22,
      20,
      6,
      4
    ],
    "1df7de8a": [
      1,
      0,
      3,
      2,
      10,
      9,
      7,
      31,
      26,
      8,
      5,
      19,
      21,
      23,
      18,
      22,
      20,
      6,
      4
    ],
    "efa36cbe": [
      1,
      0,
      3,
      2,
      10,
      9,
      7,
      31,
      26,
      8,
      5,
      19,
      21,
      23,
      18,
      22,
      20,
      6,
      4
    ],
    "a741db94": [
      1,
      0,
      3,
      2,
      10,
      9,
      7,
      31,
      26,
      8,
      5,
      19,
      21,
      23,
      18,
      22,
      20,
      6,
      4
    ],
    "16e05e3a": [
      1,
      0,
      3,
      2,
      10,
      9,
      7,
      31,
      26,
      8,
      5,
      19,
      21,
      23,
      18,
      22,
      20,
      6,
      4
    ],
    "b36e391e": [
      1,
      0,
      3,
      2,
      10,
      9,
      7,
      31,
      26,
      8,
      5,
      19,
      21,
      23,
      18,
      22,
      20,
      6,
      4
    ],
    "1eda8d0c": [
      1,
      0,
      3,
      2,
      10,
      9,
      7,
      31,
      26,
      8,
      5,
      19,
      21,
      23,
      18,
      22,
      20,
      6,
      4
    ],
    "48eb003d": [
      1,
      0,
      3,
      2,
      10,
      9,
      7,
      31,
      26,
      8,
      5,
      19,
      21,
      23,
      18,
      22,
      20,
      6,
      4
    ],
    "11cc7e86": [
      1,
      0,
      3,
      2,
      10,
      9,
      7,
      31,
      26,
      8,
      5,
      19,
      21,
      23,
      18,
      22,
      20,
      6,
      4
    ],
    "29bcaf9c": [
      1,
      0,
      3,
      2,
      10,
      9,
      7,
      31,
      26,
      8,
      5,
      19,
      21,
      23,
      18,
      22,
      20,
      6,
      4
    ],
    "58beff46": [
      1,
      0,
      3,
      2,
      10,
      9,
      7,
      31,
      26,
      8,
      5,
      19,
      21,
      23,
      18,
      22,
      20,
      6,
      4
    ],
    "2c66673c": [
      1,
      0,
      3,
      2,
      10,
      9,
      7,
      31,
      26,
      8,
      5,
      19,
      21,
      23,
      18,
      22,
      20,
      6,
      4
    ],
    "6c6cdcfc": [
      1,
      0,
      3,
      2,
      10,
      9,
      7,
      31,
      26,
      8,
      5,
      19,
      21,
      23,
      18,
      22,
      20,
      6,
      4
    ],
    "453d92ee": [
      1,
      0,
      3,
      2,
      10,
      9,
      7,
      31,
      26,
      8,
      5,
      19,
      21,
      23,
      18,
      22,
      20,
      6,
      4
    ],
    "6e7238a4": [
      1,
      0,
      3,
      2,
      10,
      9,
      7,
      31,
      26,
      8,
      5,
      19,
      21,
      23,
      18,
      22,
      20,
      6,
      4
    ],
    "4016206a": [
      1,
      0,
      3,
      2,
      10,
      9,
      7,
      31,
      26,
      8,
      5,
      19,
      21,
      23,
      18,
      22,
      20,
      6,
      4
    ],
    "46b3bee2": [
      1,
      0,
      3,
      2,
      10,
      9,
      7,
      31,
      26,
      8,
      5,
      19,
      21,
      23,
      18,
      22,
      20,
      6,
      4
    ],
    "124f66be": [
      1,
      0,
      3,
      2,
      10,
      9,
      7,
      31,
      26,
      8,
      5,
      19,
      21,
      23,
      18,
      22,
      20,
      6,
      4
    ],
    "2219c942": [
      1,
      0,
      3,
      2,
      10,
      9,
      7,
      31,
      26,
      8,
      5,
      19,
      21,
      23,
      18,
      22,
      20,
      6,
      4
    ],
    "36af8ffa": [
      1,
      0,
      3,
      2,
      10,
      9,
      7,
      31,
      26,
      8,
      5,
      19,
      21,
      23,
      18,
      22,
      20,
      6,
      4
    ],
    "79d7841e": [
      65,
      11
    ],
    "326c9dc8": [
      65,
      11
    ],
    "63bdd9a5": [
      65,
      11
    ],
    "40539bf4": [
      65,
      11
    ],
    "8da141ea": [
      65,
      11
    ],
    "76531ea6": [
      65,
      11
    ],
    "2f8877b3": [
      65,
      11
    ],
    "1628b813": [
      65,
      11
    ],
    "6fbc4fdc": [
      65,
      11
    ],
    "35b75c20": [
      65,
      11
    ],
    "7aa80c74": [
      65,
      11
    ],
    "6bb82dd6": [
      65,
      11
    ],
    "b79d39d0": [
      65,
      11
    ],
    "594d331d": [
      65,
      11
    ]
  }
}